pyMRAW.py
pymraw-0.33.0.dist-info/METADATA
pymraw-0.33.0.dist-info/WHEEL
pymraw-0.33.0.dist-info/licenses/LICENSE
pymraw-0.33.0.dist-info/RECORD
